ocular/__init__.py
ocular/api.py
ocular/config.py
ocular/core/__init__.py
ocular/core/export.py
ocular/core/project.py
ocular/core/version.py
ocular/core/workspace.py
ocular/utils/__init__.py
ocular/utils/config.py
ocular/utils/errors.py
ocular/utils/http_client.py
ocular/utils/logging.py
ocular_ai-0.0.5.dist-info/LICENSE
ocular_ai-0.0.5.dist-info/METADATA
ocular_ai-0.0.5.dist-info/WHEEL
ocular_ai-0.0.5.dist-info/RECORD
