Metadata-Version: 2.3
Name: ocular-ai
Version: 0.0.5
Summary: Official Python SDK for the Ocular AI Foundry Platform
License: Apache-2.0
Keywords: ocular,ai,machine learning,sdk,api
Author: Vivek Lahole
Author-email: vivek@useocular.com
Requires-Python: >=3.10,<4.0
Classifier: Development Status :: 4 - Beta
Classifier: Intended Audience :: Developers
Classifier: License :: OSI Approved :: Apache Software License
Classifier: Programming Language :: Python :: 3
Classifier: Programming Language :: Python :: 3.10
Classifier: Programming Language :: Python :: 3.11
Classifier: Programming Language :: Python :: 3.12
Classifier: Programming Language :: Python :: 3.13
Classifier: Topic :: Software Development :: Libraries
Requires-Dist: python-dotenv (>=0.15.0,<0.16.0)
Requires-Dist: requests (>=2.25.0,<3.0.0)
Requires-Dist: typing-extensions (>=4.1.0,<5.0.0)
Requires-Dist: urllib3 (>=1.26.0,<2.0.0)
Project-URL: Bug Tracker, https://github.com/OcularEngineering/ocular-python-sdk/issues
Project-URL: Documentation, https://docs.useocular.com
Project-URL: Homepage, https://github.com/OcularEngineering/ocular-python-sdk
Project-URL: Repository, https://github.com/OcularEngineering/ocular-python-sdk
